azure/ai/voicelive/__init__.py
azure/ai/voicelive/_patch.py
azure/ai/voicelive/_types.py
azure/ai/voicelive/_version.py
azure/ai/voicelive/py.typed
azure/ai/voicelive/_operations/__init__.py
azure/ai/voicelive/_operations/_operations.py
azure/ai/voicelive/_utils/__init__.py
azure/ai/voicelive/_utils/model_base.py
azure/ai/voicelive/_utils/serialization.py
azure/ai/voicelive/_utils/utils.py
azure/ai/voicelive/aio/__init__.py
azure/ai/voicelive/aio/_patch.py
azure/ai/voicelive/aio/_operations/__init__.py
azure/ai/voicelive/aio/_operations/_operations.py
azure/ai/voicelive/models/__init__.py
azure/ai/voicelive/models/_enums.py
azure/ai/voicelive/models/_models.py
azure/ai/voicelive/models/_patch.py
azure_ai_voicelive-1.0.0.dist-info/licenses/LICENSE
azure_ai_voicelive-1.0.0.dist-info/METADATA
azure_ai_voicelive-1.0.0.dist-info/WHEEL
azure_ai_voicelive-1.0.0.dist-info/top_level.txt
azure_ai_voicelive-1.0.0.dist-info/RECORD
