Metadata-Version: 2.4
Name: azure-ai-voicelive
Version: 1.0.0
Summary: Microsoft Corporation Azure Ai Voicelive Client Library for Python
Author-email: Microsoft Corporation <azpysdkhelp@microsoft.com>
License-Expression: MIT
Project-URL: repository, https://github.com/Azure/azure-sdk-for-python
Keywords: azure,azure sdk
Classifier: Development Status :: 5 - Production/Stable
Classifier: Programming Language :: Python
Classifier: Programming Language :: Python :: 3 :: Only
Classifier: Programming Language :: Python :: 3
Classifier: Programming Language :: Python :: 3.9
Classifier: Programming Language :: Python :: 3.10
Classifier: Programming Language :: Python :: 3.11
Classifier: Programming Language :: Python :: 3.12
Classifier: Programming Language :: Python :: 3.13
Requires-Python: >=3.9
License-File: LICENSE
Requires-Dist: isodate>=0.6.1
Requires-Dist: azure-core>=1.35.0
Requires-Dist: typing-extensions>=4.6.0
Provides-Extra: aiohttp
Requires-Dist: aiohttp<4.0.0,>=3.9.0; extra == "aiohttp"
Provides-Extra: test
Requires-Dist: pytest>=8.0; extra == "test"
Requires-Dist: pytest-asyncio>=0.23; extra == "test"
Requires-Dist: pytest-rerunfailures>=13.0; extra == "test"
Requires-Dist: aiohttp<4.0.0,>=3.9.0; extra == "test"
Requires-Dist: python-dotenv; extra == "test"
Requires-Dist: azure-identity; extra == "test"
Requires-Dist: soundfile; extra == "test"
Requires-Dist: pyaudio; (platform_python_implementation == "CPython" and python_version < "3.13") and extra == "test"
Dynamic: license-file
